jupyter_fairly/__init__.py
jupyter_fairly/_version.py
jupyter_fairly/config.py
jupyter_fairly/handlers.py
jupyter_fairly/tests/__init__.py
jupyter_fairly/tests/test_fourtu.py
jupyter_fairly/tests/test_handlers.py
jupyter_fairly-0.4.2.data/data/etc/jupyter/jupyter_notebook_config.d/jupyter_fairly.json
jupyter_fairly-0.4.2.data/data/etc/jupyter/jupyter_server_config.d/jupyter_fairly.json
jupyter_fairly-0.4.2.data/data/share/jupyter/labextensions/jupyter-fairly/build_log.json
jupyter_fairly-0.4.2.data/data/share/jupyter/labextensions/jupyter-fairly/package.json
jupyter_fairly-0.4.2.data/data/share/jupyter/labextensions/jupyter-fairly/schemas/jupyter-fairly/package.json.orig
jupyter_fairly-0.4.2.data/data/share/jupyter/labextensions/jupyter-fairly/schemas/jupyter-fairly/plugin.json
jupyter_fairly-0.4.2.data/data/share/jupyter/labextensions/jupyter-fairly/static/lib_index_js.bb1914d804cc68cedb6d.js
jupyter_fairly-0.4.2.data/data/share/jupyter/labextensions/jupyter-fairly/static/lib_index_js.bb1914d804cc68cedb6d.js.map
jupyter_fairly-0.4.2.data/data/share/jupyter/labextensions/jupyter-fairly/static/remoteEntry.d810f4cdb96f14df7570.js
jupyter_fairly-0.4.2.data/data/share/jupyter/labextensions/jupyter-fairly/static/remoteEntry.d810f4cdb96f14df7570.js.map
jupyter_fairly-0.4.2.data/data/share/jupyter/labextensions/jupyter-fairly/static/style.js
jupyter_fairly-0.4.2.data/data/share/jupyter/labextensions/jupyter-fairly/static/style_index_js.2b82700c3ba47712b002.js
jupyter_fairly-0.4.2.data/data/share/jupyter/labextensions/jupyter-fairly/static/style_index_js.2b82700c3ba47712b002.js.map
jupyter_fairly-0.4.2.data/data/share/jupyter/labextensions/jupyter-fairly/static/vendors-node_modules_css-loader_dist_runtime_api_js-node_modules_css-loader_dist_runtime_cssW-72eba1.eeaf8d5f866ec1aeceb3.js
jupyter_fairly-0.4.2.dist-info/METADATA
jupyter_fairly-0.4.2.dist-info/WHEEL
jupyter_fairly-0.4.2.dist-info/licenses/LICENSE
jupyter_fairly-0.4.2.dist-info/RECORD
