Metadata-Version: 2.3
Name: jupyter_fairly
Version: 0.4.2
Dynamic: Keywords
Summary: A JupyterLab extension for seamless integration of Jupyter-based research environments and research data repositories
Project-URL: Homepage, https://github.com/ITC-CRIB/jupyter-fairly
Project-URL: Bug Tracker, https://github.com/ITC-CRIB/jupyter-fairly/issues
Project-URL: Repository, https://github.com/ITC-CRIB/jupyter-fairly.git
Author-email: "Manuel G. Garcia, Serkan Girgin, Jose Urra Llanusa" <m.g.garciaalvarez@tudelft.nl>
License: BSD 3-Clause License
License-File: LICENSE
Classifier: Framework :: Jupyter
Classifier: Framework :: Jupyter :: JupyterLab
Classifier: Framework :: Jupyter :: JupyterLab :: 3
Classifier: Framework :: Jupyter :: JupyterLab :: Extensions
Classifier: Framework :: Jupyter :: JupyterLab :: Extensions :: Prebuilt
Classifier: License :: OSI Approved :: BSD License
Classifier: Programming Language :: Python
Classifier: Programming Language :: Python :: 3
Classifier: Programming Language :: Python :: 3.8
Classifier: Programming Language :: Python :: 3.9
Classifier: Programming Language :: Python :: 3.10
Classifier: Programming Language :: Python :: 3.11
Requires-Python: >=3.8
Requires-Dist: fairly==0.4.1
Requires-Dist: jupyter-server<3,>=1.21
Requires-Dist: jupyterlab<4,>=3.6.1
Provides-Extra: test
Requires-Dist: coverage; extra == 'test'
Requires-Dist: pytest; extra == 'test'
Requires-Dist: pytest-asyncio; extra == 'test'
Requires-Dist: pytest-cov; extra == 'test'
Requires-Dist: pytest-jupyter[server]>=0.6.0; extra == 'test'
